pylib/__init__.py
pylib/core.py
yaowei_pylib-0.1.3.dist-info/METADATA
yaowei_pylib-0.1.3.dist-info/WHEEL
yaowei_pylib-0.1.3.dist-info/top_level.txt
yaowei_pylib-0.1.3.dist-info/RECORD
